setup.py
aloft/__init__.py
aloft/arguments.py
aloft/aws.py
aloft/chart.py
aloft/chart_config.py
aloft/cluster.py
aloft/cluster_config.py
aloft/config.py
aloft/host.py
aloft/input.py
aloft/k8s.py
aloft/kubeconfig.py
aloft/output.py
aloft/process.py
aloft/volume.py
aloft/vpc.py
aloft.egg-info/PKG-INFO
aloft.egg-info/SOURCES.txt
aloft.egg-info/dependency_links.txt
aloft.egg-info/not-zip-safe
aloft.egg-info/requires.txt
aloft.egg-info/top_level.txt
bin/aloft