Metadata-Version: 1.2
Name: aloft
Version: 0.4.5
Summary: Tool to manage Kubernetes clusters and helm charts across multiple AWS accounts and clusters
Home-page: UNKNOWN
License: UNKNOWN
Platform: UNKNOWN
Requires-Python: >=3.6
